{
  "name": "hr-osc",
  "frontend:build": "npm run build",
  "frontend:install": "npm install",
  "frontend:dev": "",
  "frontend:dev:watcher": "npm run dev",
  "wailsjsdir": "./frontend/dist",
  "version": "2",
  "Path": "",
  "BuildDir": "",
  "outputfilename": "hr-osc.exe",
  "OutputType": "",
  "Platform": "",
  "runNonNativeBuildHooks": false,
  "postBuildHooks": null,
  "Author": {
    "name": "Byeon Seongun",
    "email": "kamyu@kamyu.me"
  },
  "Info": {
    "companyName": "hr-osc",
    "productName": "hr-osc",
    "productVersion": "1.0.0",
    "copyright": "Copyright kamyu1537",
    "comments": "Stromno Client for VRChat OSC"
  },
  "debounceMS": 100,
  "devserverurl": "http://localhost:34115",
  "appargs": "",
  "nsisType": ""
}
